airo_robots/__init__.py
airo_robots/awaitable_action.py
airo_robots/exceptions.py
airo_robots/hardware_interaction_utils.py
airo_robots/py.typed
airo_robots/drives/__init__.py
airo_robots/drives/mobile_robot.py
airo_robots/drives/hardware/__init__.py
airo_robots/drives/hardware/kelo_robile.py
airo_robots/drives/hardware/manual_robot_testing.py
airo_robots/grippers/__init__.py
airo_robots/grippers/parallel_position_gripper.py
airo_robots/grippers/hardware/__init__.py
airo_robots/grippers/hardware/manual_gripper_testing.py
airo_robots/grippers/hardware/robotiq_2f85_urcap.py
airo_robots/grippers/hardware/schunk_process.py
airo_robots/manipulators/__init__.py
airo_robots/manipulators/bimanual_position_manipulator.py
airo_robots/manipulators/force_torque_sensor.py
airo_robots/manipulators/position_manipulator.py
airo_robots/manipulators/hardware/__init__.py
airo_robots/manipulators/hardware/manual_execute_trajectory_testing.py
airo_robots/manipulators/hardware/manual_manipulator_testing.py
airo_robots/manipulators/hardware/ur_rtde.py
airo_robots-2026.1.0.dist-info/METADATA
airo_robots-2026.1.0.dist-info/WHEEL
airo_robots-2026.1.0.dist-info/top_level.txt
airo_robots-2026.1.0.dist-info/RECORD
