Metadata-Version: 2.4
Name: airo_robots
Version: 2026.1.0
Summary: Interfaces, hardware implementations of those interfaces and other functionalities to control robot manipulators and grippers at the Ghent University AI and Robotics Lab
Author: Thomas Lips
Author-email: thomas.lips@ugent.be
Requires-Dist: numpy>=2.0
Requires-Dist: ur-rtde>=1.5.7
Requires-Dist: click
Requires-Dist: airo-typing>=2026.1.0
Requires-Dist: airo-spatial-algebra>=2026.1.0
Requires-Dist: airo-tulip>=0.4.0
Dynamic: author
Dynamic: author-email
Dynamic: requires-dist
Dynamic: summary
